uaconnect/__about__.py
uaconnect/__init__.py
uaconnect/consumer.py
uaconnect/filter.py
uaconnect/recorder.py
uaconnect/ext/__init__.py
uaconnect/ext/redisrecorder.py
uaconnect-1.0.2.dist-info/METADATA
uaconnect-1.0.2.dist-info/WHEEL
uaconnect-1.0.2.dist-info/top_level.txt
uaconnect-1.0.2.dist-info/RECORD
