Metadata-Version: 2.1
Name: uaconnect
Version: 1.0.2
Summary: Python package for using Airship Real-Time Data Streaming
Home-page: https://airship.com/
Author: Airship Tools
Author-email: tools@airship.com
License: Apache v2
Classifier: Development Status :: 5 - Production/Stable
Classifier: Intended Audience :: Developers
Classifier: License :: OSI Approved :: Apache Software License
Classifier: Operating System :: OS Independent
Classifier: Topic :: Software Development :: Libraries
Requires-Dist: requests (>=2.27)
